[
  {
    "player": "Derin",
    "source": "Level 20 rare Crypt",
    "chest": "Rare Dragon Chest",
    "score": 319
  },
  {
    "player": "Princess Noli",
    "source": "Level 10 Crypt",
    "chest": "Cobra Chest",
    "score": 35
  },
  {
    "player": "Princess Noli",
    "source": "Level 5 Crypt",
    "chest": "Cobra Chest",
    "score": 13
  },
  {
    "player": "Derin",
    "source": "Level 25 rare Crypt",
    "chest": "Rare Dragon Chest",
    "score": 800
  },
  {
    "player": "Princess Noli",
    "source": "Level 15 Crypt",
    "chest": "Mayan Chest",
    "score": 75
  },
  {
    "player": "Thutmose III",
    "source": "Level 15 Citadel",
    "chest": "Elven Citadel Chest",
    "score": 30
  },
  {
    "player": "Princess Noli",
    "source": "Level 5 Crypt",
    "chest": "Cobra Chest",
    "score": 13
  },
  {
    "player": "Princess Noli",
    "source": "Level 10 Crypt",
    "chest": "Mayan Chest",
    "score": 35
  },
  {
    "player": "Derin",
    "source": "Level 20 Crypt",
    "chest": "Barbarian Chest",
    "score": 167
  },
  {
    "player": "Derin",
    "source": "Level 15 Crypt",
    "chest": "Elegant Chest",
    "score": 75
  },
  {
    "player": "Derin",
    "source": "Level 25 epic Crypt",
    "chest": "Braided Chest",
    "score": 1000
  },
  {
    "player": "Derin",
    "source": "Level 25 epic Crypt",
    "chest": "Scorpion Chest",
    "score": 1000
  },
  {
    "player": "Derin",
    "source": "Level 15 Crypt",
    "chest": "Fire Chest",
    "score": 75
  },
  {
    "player": "Derin",
    "source": "Level 20 Crypt",
    "chest": "Orc Chest",
    "score": 167
  },
  {
    "player": "Derin",
    "source": "Level 25 Crypt",
    "chest": "Mayan Chest",
    "score": 550
  },
  {
    "player": "Eulàlia",
    "source": "Level 20 epic Crypt",
    "chest": "Titansteel Chest",
    "score": 598
  },
  {
    "player": "Eulàlia",
    "source": "Level 15 epic Crypt",
    "chest": "Chest of the Cursed",
    "score": 308
  },
  {
    "player": "Eydanen",
    "source": "Level 30 rare Crypt",
    "chest": "Rare Dragon Chest",
    "score": 1200
  },
  {
    "player": "Eufrozyna",
    "source": "Level 20 epic Crypt",
    "chest": "Harpy Chest",
    "score": 598
  },
  {
    "player": "Eydanen",
    "source": "Level 25 Crypt",
    "chest": "Fire Chest",
    "score": 550
  },
  {
    "player": "Eufrozyna",
    "source": "Level 20 epic Crypt",
    "chest": "Cobalt Chest",
    "score": 598
  },
  {
    "player": "Povilinskas",
    "source": "Level 30 rare Crypt",
    "chest": "Rare Dragon Chest",
    "score": 1200
  },
  {
    "player": "Eydanen",
    "source": "Level 20 Crypt",
    "chest": "Fire Chest",
    "score": 167
  },
  {
    "player": "Eydanen",
    "source": "Level 15 Crypt",
    "chest": "Fire Chest",
    "score": 75
  },
  {
    "player": "Eufrozyna",
    "source": "Level 20 Crypt",
    "chest": "Elegant Chest",
    "score": 167
  },
  {
    "player": "Lord Farquaad",
    "source": "Level 5 Crypt",
    "chest": "Bone Chest",
    "score": 13
  },
  {
    "player": "CrixusX2",
    "source": "Level 5 Crypt",
    "chest": "Bone Chest",
    "score": 13
  },
  {
    "player": "Povilinskas",
    "source": "Level 25 epic Crypt",
    "chest": "Barbarian Chest",
    "score": 1000
  },
  {
    "player": "CrixusX2",
    "source": "Level 5 Crypt",
    "chest": "Fire Chest",
    "score": 13
  },
  {
    "player": "Maverick",
    "source": "Level 10 Crypt",
    "chest": "Barbarian Chest",
    "score": 35
  },
  {
    "player": "Eufrozyna",
    "source": "Level 20 Crypt",
    "chest": "Orc Chest",
    "score": 167
  },
  {
    "player": "Eydanen",
    "source": "Level 15 Crypt",
    "chest": "Fire Chest",
    "score": 75
  },
  {
    "player": "CrixusX2",
    "source": "Level 5 Crypt",
    "chest": "#NAME?",
    "score": 13
  },
  {
    "player": "Maverick",
    "source": "Level 5 Crypt",
    "chest": "Forgotten Chest",
    "score": 13
  },
  {
    "player": "Maverick",
    "source": "Level 15 Crypt",
    "chest": "Sand Chest",
    "score": 75
  },
  {
    "player": "Lord Farquaad",
    "source": "Level 15 Crypt",
    "chest": "Orc Chest",
    "score": 75
  },
  {
    "player": "Eufrozyna",
    "source": "Level 20 Crypt",
    "chest": "Fire Chest",
    "score": 167
  },
  {
    "player": "Eufrozyna",
    "source": "Carrot Monster",
    "chest": "Carrot Chest",
    "score": 0
  },
  {
    "player": "Maverick",
    "source": "Level 25 epic Crypt",
    "chest": "Abandoned Chest",
    "score": 1000
  },
  {
    "player": "Lord Farquaad",
    "source": "Level 10 Crypt",
    "chest": "Barbarian Chest",
    "score": 35
  },
  {
    "player": "Dire Wolf",
    "source": "Carrot Monster",
    "chest": "Carrot Chest",
    "score": 0
  },
  {
    "player": "Maverick",
    "source": "Level 20 Crypt",
    "chest": "Fire Chest",
    "score": 167
  },
  {
    "player": "Conquer Of Universe",
    "source": "Carrot Monster",
    "chest": "Carrot Chest",
    "score": 0
  },
  {
    "player": "Lord Farquaad",
    "source": "Level 15 Crypt",
    "chest": "Orc Chest",
    "score": 75
  },
  {
    "player": "Maverick",
    "source": "Level 20 epic Crypt",
    "chest": "Abandoned Chest",
    "score": 598
  },
  {
    "player": "Maverick",
    "source": "Level 5 Crypt",
    "chest": "Forgotten Chest",
    "score": 13
  },
  {
    "player": "Maverick",
    "source": "Level 10 Crypt",
    "chest": "Cobra Chest",
    "score": 35
  },
  {
    "player": "Povilinskas",
    "source": "Carrot Monster",
    "chest": "Carrot Chest",
    "score": 0
  },
  {
    "player": "Maverick",
    "source": "Level 10 Crypt",
    "chest": "Elegant Chest",
    "score": 35
  },
  {
    "player": "CrixusX2",
    "source": "Level 25 rare Crypt",
    "chest": "Rare Dragon Chest",
    "score": 800
  },
  {
    "player": "CrixusX2",
    "source": "Level 25 rare Crypt",
    "chest": "Rare Dragon Chest",
    "score": 800
  },
  {
    "player": "PUBLIC ENEMY",
    "source": "Level 15 Crypt",
    "chest": "Forgotten Chest",
    "score": 75
  },
  {
    "player": "CrixusX2",
    "source": "Level 25 rare Crypt",
    "chest": "Rare Dragon Chest",
    "score": 800
  },
  {
    "player": "Mspawn311",
    "source": "Level 15 Crypt",
    "chest": "Barbarian Chest",
    "score": 75
  },
  {
    "player": "CrixusX2",
    "source": "Level 20 Crypt",
    "chest": "Orc Chest",
    "score": 167
  },
  {
    "player": "Mspawn311",
    "source": "Level 15 Crypt",
    "chest": "Stone Chest",
    "score": 75
  },
  {
    "player": "CrixusX2",
    "source": "Level 20 Crypt",
    "chest": "Orc Chest",
    "score": 167
  },
  {
    "player": "Mspawn311",
    "source": "Level 15 Crypt",
    "chest": "Gnome Workshop Chest",
    "score": 75
  },
  {
    "player": "CrixusX2",
    "source": "Level 20 Crypt",
    "chest": "Orc Chest",
    "score": 167
  },
  {
    "player": "raïley",
    "source": "Level 25 Crypt",
    "chest": "Orc Chest",
    "score": 550
  },
  {
    "player": "Lord Farquaad",
    "source": "Carrot Monster",
    "chest": "Carrot Chest",
    "score": 0
  },
  {
    "player": "Linfiren",
    "source": "Carrot Monster",
    "chest": "Carrot Chest",
    "score": 0
  },
  {
    "player": "Mspawn311",
    "source": "Level 15 Crypt",
    "chest": "Bone Chest",
    "score": 75
  },
  {
    "player": "raïley",
    "source": "Level 25 Crypt",
    "chest": "Orc Chest",
    "score": 550
  },
  {
    "player": "Povilinskas",
    "source": "Level 10 Crypt",
    "chest": "Barbarian Chest",
    "score": 35
  },
  {
    "player": "Linfiren",
    "source": "Carrot Monster",
    "chest": "Carrot Chest",
    "score": 0
  },
  {
    "player": "Kristoff Maximus",
    "source": "Level 25 Crypt",
    "chest": "Forgotten Chest",
    "score": 550
  },
  {
    "player": "Kristoff Maximus",
    "source": "Level 25 Crypt",
    "chest": "Barbarian Chest",
    "score": 550
  },
  {
    "player": "PUBLIC ENEMY",
    "source": "Level 15 epic Crypt",
    "chest": "Ancient Warrior's Chest",
    "score": 308
  },
  {
    "player": "Mspawn311",
    "source": "Level 20 Crypt",
    "chest": "Gnome Workshop Chest",
    "score": 167
  },
  {
    "player": "Kristoff Maximus",
    "source": "Level 25 Crypt",
    "chest": "Elegant Chest",
    "score": 550
  },
  {
    "player": "raïley",
    "source": "Arena",
    "chest": "Gladiator's Chest",
    "score": 30
  },
  {
    "player": "Mspawn311",
    "source": "Level 20 epic Crypt",
    "chest": "Abandoned Chest",
    "score": 598
  },
  {
    "player": "Linfiren",
    "source": "Carrot Monster",
    "chest": "Carrot Chest",
    "score": 0
  },
  {
    "player": "PUBLIC ENEMY",
    "source": "Level 15 epic Crypt",
    "chest": "Scorpion Chest",
    "score": 308
  },
  {
    "player": "Beanara",
    "source": "Arena",
    "chest": "Gladiator's Chest",
    "score": 30
  },
  {
    "player": "YLLIABEL",
    "source": "Level 15 Crypt",
    "chest": "Forgotten Chest",
    "score": 75
  },
  {
    "player": "PUBLIC ENEMY",
    "source": "Level 15 epic Crypt",
    "chest": "White Wood Chest",
    "score": 308
  },
  {
    "player": "Eulàlia",
    "source": "Level 15 Crypt",
    "chest": "Stone Chest",
    "score": 75
  },
  {
    "player": "Kristoff Maximus",
    "source": "Level 30 epic Crypt",
    "chest": "Titansteel Chest",
    "score": 1184
  },
  {
    "player": "Beanara",
    "source": "Level 20 rare Crypt",
    "chest": "Rare Dragon Chest",
    "score": 319
  },
  {
    "player": "Atilla",
    "source": "Level 15 Crypt",
    "chest": "Bone Chest",
    "score": 75
  },
  {
    "player": "Eulàlia",
    "source": "Level 15 Crypt",
    "chest": "Forgotten Chest",
    "score": 75
  },
  {
    "player": "Beanara",
    "source": "Level 20 rare Crypt",
    "chest": "Rare Dragon Chest",
    "score": 319
  },
  {
    "player": "Eulàlia",
    "source": "Level 15 Crypt",
    "chest": "Stone Chest",
    "score": 75
  },
  {
    "player": "Odysseus",
    "source": "Level 25 rare Crypt",
    "chest": "Rare Dragon Chest",
    "score": 800
  },
  {
    "player": "Beanara",
    "source": "Level 20 rare Crypt",
    "chest": "Rare Dragon Chest",
    "score": 319
  },
  {
    "player": "YLLIABEL",
    "source": "Level 15 Crypt",
    "chest": "Bone Chest",
    "score": 75
  },
  {
    "player": "Odysseus",
    "source": "Level 25 rare Crypt",
    "chest": "Rare Dragon Chest",
    "score": 800
  },
  {
    "player": "Beanara",
    "source": "Level 20 rare Crypt",
    "chest": "Rare Dragon Chest",
    "score": 319
  },
  {
    "player": "Odysseus",
    "source": "Level 25 rare Crypt",
    "chest": "Rare Dragon Chest",
    "score": 800
  },
  {
    "player": "WraithStriker",
    "source": "Level 15 Crypt",
    "chest": "Elegant Chest",
    "score": 75
  },
  {
    "player": "Odysseus",
    "source": "Level 25 rare Crypt",
    "chest": "Rare Dragon Chest",
    "score": 800
  },
  {
    "player": "WraithStriker",
    "source": "Level 10 Crypt",
    "chest": "Forgotten Chest",
    "score": 35
  },
  {
    "player": "WraithStriker",
    "source": "Level 15 Crypt",
    "chest": "Elegant Chest",
    "score": 75
  },
  {
    "player": "Odysseus",
    "source": "Level 25 rare Crypt",
    "chest": "Rare Dragon Chest",
    "score": 800
  },
  {
    "player": "YLLIABEL",
    "source": "Level 15 rare Crypt",
    "chest": "Rare Dragon Chest",
    "score": 130
  },
  {
    "player": "Odysseus",
    "source": "Level 25 Crypt",
    "chest": "Sand Chest",
    "score": 550
  },
  {
    "player": "Beanara",
    "source": "Level 20 rare Crypt",
    "chest": "Rare Dragon Chest",
    "score": 319
  },
  {
    "player": "Odysseus",
    "source": "Level 25 Crypt",
    "chest": "Cobra Chest",
    "score": 550
  },
  {
    "player": "Beanara",
    "source": "Level 20 rare Crypt",
    "chest": "Rare Dragon Chest",
    "score": 319
  },
  {
    "player": "Odysseus",
    "source": "Level 25 Crypt",
    "chest": "Barbarian Chest",
    "score": 550
  },
  {
    "player": "Odysseus",
    "source": "Level 25 Crypt",
    "chest": "Elegant Chest",
    "score": 550
  },
  {
    "player": "Odysseus",
    "source": "Level 25 Crypt",
    "chest": "Barbarian Chest",
    "score": 550
  },
  {
    "player": "Beanara",
    "source": "Level 20 Crypt",
    "chest": "Barbarian Chest",
    "score": 167
  },
  {
    "player": "Odysseus",
    "source": "Level 25 Crypt",
    "chest": "Elegant Chest",
    "score": 550
  },
  {
    "player": "Odysseus",
    "source": "Level 25 Crypt",
    "chest": "Forgotten Chest",
    "score": 550
  },
  {
    "player": "Beanara",
    "source": "Level 20 Crypt",
    "chest": "Orc Chest",
    "score": 167
  },
  {
    "player": "YLLIABEL",
    "source": "Level 20 rare Crypt",
    "chest": "Rare Dragon Chest",
    "score": 319
  },
  {
    "player": "Folinan BOW",
    "source": "Clan wealth",
    "chest": "Common Chest of Wealth",
    "score": 0
  },
  {
    "player": "Folinan BOW",
    "source": "Clan wealth",
    "chest": "Uncommon Chest of Wealth",
    "score": 0
  },
  {
    "player": "Folinan BOW",
    "source": "Clan wealth",
    "chest": "Rare Chest of Wealth",
    "score": 0
  },
  {
    "player": "Folinan BOW",
    "source": "Clan wealth",
    "chest": "Epic Chest of Wealth",
    "score": 0
  },
  {
    "player": "Odysseus",
    "source": "Level 25 Crypt",
    "chest": "Forgotten Chest",
    "score": 550
  },
  {
    "player": "Odysseus",
    "source": "Level 25 Crypt",
    "chest": "Fire Chest",
    "score": 550
  },
  {
    "player": "Beanara",
    "source": "Level 20 Crypt",
    "chest": "Stone Chest",
    "score": 167
  },
  {
    "player": "Odysseus",
    "source": "Level 25 Crypt",
    "chest": "Cobra Chest",
    "score": 550
  },
  {
    "player": "Beanara",
    "source": "Level 20 Crypt",
    "chest": "Bone Chest",
    "score": 167
  },
  {
    "player": "Odysseus",
    "source": "Level 25 epic Crypt",
    "chest": "Trillium Chest",
    "score": 1000
  },
  {
    "player": "Eulàlia",
    "source": "Level 15 Crypt",
    "chest": "Stone Chest",
    "score": 75
  },
  {
    "player": "Odysseus",
    "source": "Level 25 epic Crypt",
    "chest": "Ancient Bastion Chest",
    "score": 1000
  },
  {
    "player": "Odysseus",
    "source": "Level 25 epic Crypt",
    "chest": "Titansteel Chest",
    "score": 1000
  },
  {
    "player": "Odysseus",
    "source": "Level 25 epic Crypt",
    "chest": "Scorpion Chest",
    "score": 1000
  },
  {
    "player": "Odysseus",
    "source": "Level 25 epic Crypt",
    "chest": "Trillium Chest",
    "score": 1000
  },
  {
    "player": "Linfiren",
    "source": "Carrot Monster",
    "chest": "Carrot Chest",
    "score": 0
  },
  {
    "player": "YLLIABEL",
    "source": "Level 10 Crypt",
    "chest": "Gnome Workshop Chest",
    "score": 35
  },
  {
    "player": "Atilla",
    "source": "Level 20 Crypt",
    "chest": "Infernal Chest",
    "score": 167
  },
  {
    "player": "Atilla",
    "source": "Level 20 Crypt",
    "chest": "Sand Chest",
    "score": 167
  },
  {
    "player": "Atilla",
    "source": "Level 20 epic Crypt",
    "chest": "Titansteel Chest",
    "score": 598
  },
  {
    "player": "YLLIABEL",
    "source": "Level 15 rare Crypt",
    "chest": "Rare Dragon Chest",
    "score": 130
  },
  {
    "player": "Linfiren",
    "source": "Level 15 Crypt",
    "chest": "Orc Chest",
    "score": 75
  },
  {
    "player": "Linfiren",
    "source": "Level 10 Crypt",
    "chest": "Forgotten Chest",
    "score": 35
  },
  {
    "player": "raïley",
    "source": "Carrot Monster",
    "chest": "Carrot Chest",
    "score": 0
  },
  {
    "player": "Atilla",
    "source": "Arena",
    "chest": "Gladiator's Chest",
    "score": 30
  },
  {
    "player": "Atilla",
    "source": "Level 20 Crypt",
    "chest": "Gnome Workshop Chest",
    "score": 167
  },
  {
    "player": "Morarn",
    "source": "Level 15 Crypt",
    "chest": "Elegant Chest",
    "score": 75
  },
  {
    "player": "Morarn",
    "source": "Level 10 Crypt",
    "chest": "Mayan Chest",
    "score": 35
  },
  {
    "player": "Salka",
    "source": "Level 17 heroic Monster",
    "chest": "Elven Chest",
    "score": 110
  },
  {
    "player": "Morarn",
    "source": "Level 10 Crypt",
    "chest": "Elegant Chest",
    "score": 35
  },
  {
    "player": "Ironside",
    "source": "Carrot Monster",
    "chest": "Carrot Chest",
    "score": 0
  },
  {
    "player": "Artur",
    "source": "Level 15 Crypt",
    "chest": "Infernal Chest",
    "score": 75
  },
  {
    "player": "Artur",
    "source": "Level 25 Citadel",
    "chest": "Cursed Citadel Chest",
    "score": 120
  },
  {
    "player": "Atilla",
    "source": "Level 25 Crypt",
    "chest": "Forgotten Chest",
    "score": 550
  },
  {
    "player": "Bomrin",
    "source": "Carrot Monster",
    "chest": "Carrot Chest",
    "score": 0
  },
  {
    "player": "Thutmose III",
    "source": "Level 20 epic Crypt",
    "chest": "Trillium Chest",
    "score": 598
  },
  {
    "player": "Thutmose III",
    "source": "Level 20 Crypt",
    "chest": "Elegant Chest",
    "score": 167
  },
  {
    "player": "Thutmose III",
    "source": "Level 15 Citadel",
    "chest": "Elven Citadel Chest",
    "score": 30
  },
  {
    "player": "Moraima",
    "source": "Level 15 Crypt",
    "chest": "Fire Chest",
    "score": 75
  },
  {
    "player": "Moraima",
    "source": "Level 15 Crypt",
    "chest": "Fire Chest",
    "score": 75
  },
  {
    "player": "Bomrin",
    "source": "Level 20 Crypt",
    "chest": "Infernal Chest",
    "score": 167
  },
  {
    "player": "Thutmose III",
    "source": "Level 20 Crypt",
    "chest": "Forgotten Chest",
    "score": 167
  },
  {
    "player": "Thutmose III",
    "source": "Level 20 Crypt",
    "chest": "Mayan Chest",
    "score": 167
  },
  {
    "player": "Moraima",
    "source": "Level 5 Crypt",
    "chest": "Forgotten Chest",
    "score": 13
  },
  {
    "player": "Arevenilas",
    "source": "Level 20 Crypt",
    "chest": "Infernal Chest",
    "score": 167
  },
  {
    "player": "Arevenilas",
    "source": "Level 20 Crypt",
    "chest": "Forgotten Chest",
    "score": 167
  },
  {
    "player": "Povilinskas",
    "source": "Level 25 Crypt",
    "chest": "Bone Chest",
    "score": 550
  },
  {
    "player": "Thutmose III",
    "source": "Level 15 Citadel",
    "chest": "Elven Citadel Chest",
    "score": 30
  },
  {
    "player": "MiniAdo",
    "source": "Level 20 Crypt",
    "chest": "Orc Chest",
    "score": 167
  },
  {
    "player": "Thutmose III",
    "source": "Level 10 Citadel",
    "chest": "Elven Citadel Chest",
    "score": 18
  },
  {
    "player": "MiniAdo",
    "source": "Level 20 Crypt",
    "chest": "Elegant Chest",
    "score": 167
  },
  {
    "player": "Povilinskas",
    "source": "Level 30 rare Crypt",
    "chest": "Rare Dragon Chest",
    "score": 1200
  },
  {
    "player": "MiniAdo",
    "source": "Level 20 Crypt",
    "chest": "Cobra Chest",
    "score": 167
  },
  {
    "player": "Povilinskas",
    "source": "Level 25 Crypt",
    "chest": "Fire Chest",
    "score": 550
  },
  {
    "player": "MiniAdo",
    "source": "Level 20 rare Crypt",
    "chest": "Rare Dragon Chest",
    "score": 319
  },
  {
    "player": "MiniAdo",
    "source": "Level 20 rare Crypt",
    "chest": "Rare Dragon Chest",
    "score": 319
  },
  {
    "player": "PUBLIC ENEMY",
    "source": "Carrot Monster",
    "chest": "Carrot Chest",
    "score": 0
  },
  {
    "player": "Povilinskas",
    "source": "Level 10 rare Crypt",
    "chest": "Rare Dragon Chest",
    "score": 66
  },
  {
    "player": "Ankayel",
    "source": "Level 10 Crypt",
    "chest": "Forgotten Chest",
    "score": 35
  },
  {
    "player": "PUBLIC ENEMY",
    "source": "Carrot Monster",
    "chest": "Carrot Chest",
    "score": 0
  },
  {
    "player": "Arevenilas",
    "source": "Level 20 rare Crypt",
    "chest": "Rare Dragon Chest",
    "score": 319
  },
  {
    "player": "Ankayel",
    "source": "Level 10 Crypt",
    "chest": "Forgotten Chest",
    "score": 35
  },
  {
    "player": "Ankayel",
    "source": "Level 25 Crypt",
    "chest": "Infernal Chest",
    "score": 550
  },
  {
    "player": "Ankayel",
    "source": "Carrot Monster",
    "chest": "Carrot Chest",
    "score": 0
  },
  {
    "player": "Beanara",
    "source": "Level 20 Crypt",
    "chest": "Forgotten Chest",
    "score": 167
  },
  {
    "player": "Beanara",
    "source": "Level 20 Crypt",
    "chest": "Forgotten Chest",
    "score": 167
  },
  {
    "player": "Beanara",
    "source": "Level 20 rare Crypt",
    "chest": "Rare Dragon Chest",
    "score": 319
  },
  {
    "player": "Beanara",
    "source": "Level 20 rare Crypt",
    "chest": "Rare Dragon Chest",
    "score": 319
  },
  {
    "player": "Thutmose III",
    "source": "Level 10 rare Crypt",
    "chest": "Rare Dragon Chest",
    "score": 66
  },
  {
    "player": "Arevenilas",
    "source": "Level 20 Crypt",
    "chest": "Bone Chest",
    "score": 167
  },
  {
    "player": "Damon",
    "source": "Level 25 Crypt",
    "chest": "Orc Chest",
    "score": 550
  },
  {
    "player": "Skënderbeu",
    "source": "Level 20 epic Crypt",
    "chest": "Cobalt Chest",
    "score": 598
  },
  {
    "player": "Skënderbeu",
    "source": "Level 20 epic Crypt",
    "chest": "House of Horrors Chest",
    "score": 598
  },
  {
    "player": "Skënderbeu",
    "source": "Level 20 epic Crypt",
    "chest": "Scarab Chest",
    "score": 598
  },
  {
    "player": "Bomrin",
    "source": "Level 25 epic Crypt",
    "chest": "Scorpion Chest",
    "score": 1000
  },
  {
    "player": "Bomrin",
    "source": "Level 25 epic Crypt",
    "chest": "Braided Chest",
    "score": 1000
  },
  {
    "player": "Skënderbeu",
    "source": "Level 25 Crypt",
    "chest": "Stone Chest",
    "score": 550
  },
  {
    "player": "Skënderbeu",
    "source": "Level 25 Crypt",
    "chest": "Stone Chest",
    "score": 550
  },
  {
    "player": "Skënderbeu",
    "source": "Level 25 Crypt",
    "chest": "Stone Chest",
    "score": 550
  },
  {
    "player": "Skënderbeu",
    "source": "Level 25 Crypt",
    "chest": "Stone Chest",
    "score": 550
  },
  {
    "player": "Skënderbeu",
    "source": "Level 25 Crypt",
    "chest": "Stone Chest",
    "score": 550
  },
  {
    "player": "Skënderbeu",
    "source": "Level 25 Crypt",
    "chest": "Stone Chest",
    "score": 550
  },
  {
    "player": "Skënderbeu",
    "source": "Level 25 Crypt",
    "chest": "Stone Chest",
    "score": 550
  },
  {
    "player": "Skënderbeu",
    "source": "Level 25 Crypt",
    "chest": "Stone Chest",
    "score": 550
  },
  {
    "player": "Skënderbeu",
    "source": "Level 25 Crypt",
    "chest": "Stone Chest",
    "score": 550
  },
  {
    "player": "Skënderbeu",
    "source": "Level 25 Crypt",
    "chest": "Stone Chest",
    "score": 550
  },
  {
    "player": "Skënderbeu",
    "source": "Level 25 Crypt",
    "chest": "Stone Chest",
    "score": 550
  },
  {
    "player": "GM Maximus",
    "source": "Level 30 rare Crypt",
    "chest": "Rare Dragon Chest",
    "score": 1200
  },
  {
    "player": "GM Maximus",
    "source": "Level 10 Crypt",
    "chest": "Fire Chest",
    "score": 35
  },
  {
    "player": "GM Maximus",
    "source": "Level 20 Crypt",
    "chest": "Gnome Workshop Chest",
    "score": 167
  },
  {
    "player": "GM Maximus",
    "source": "Level 20 epic Crypt",
    "chest": "Titansteel Chest",
    "score": 598
  },
  {
    "player": "GM Maximus",
    "source": "Level 15 rare Crypt",
    "chest": "Rare Dragon Chest",
    "score": 130
  },
  {
    "player": "GM Maximus",
    "source": "Level 20 rare Crypt",
    "chest": "Rare Dragon Chest",
    "score": 319
  },
  {
    "player": "GM Maximus",
    "source": "Level 15 rare Crypt",
    "chest": "Rare Dragon Chest",
    "score": 130
  },
  {
    "player": "GM Maximus",
    "source": "Level 20 epic Crypt",
    "chest": "Scorpion Chest",
    "score": 598
  },
  {
    "player": "GM Maximus",
    "source": "Level 20 Crypt",
    "chest": "Infernal Chest",
    "score": 167
  },
  {
    "player": "GM Maximus",
    "source": "Level 25 epic Crypt",
    "chest": "Minotaur Chest",
    "score": 1000
  },
  {
    "player": "GM Maximus",
    "source": "Level 25 Crypt",
    "chest": "Elegant Chest",
    "score": 550
  },
  {
    "player": "GM Maximus",
    "source": "Level 25 rare Crypt",
    "chest": "Rare Dragon Chest",
    "score": 800
  },
  {
    "player": "GM Maximus",
    "source": "Level 20 epic Crypt",
    "chest": "Ancient Warrior's Chest",
    "score": 598
  },
  {
    "player": "SBD",
    "source": "Level 10 Crypt",
    "chest": "Orc Chest",
    "score": 35
  },
  {
    "player": "SBD",
    "source": "Level 5 Crypt",
    "chest": "Cobra Chest",
    "score": 13
  },
  {
    "player": "SBD",
    "source": "Level 15 Crypt",
    "chest": "Infernal Chest",
    "score": 75
  },
  {
    "player": "GM Maximus",
    "source": "Level 20 Crypt",
    "chest": "Infernal Chest",
    "score": 167
  },
  {
    "player": "GM Maximus",
    "source": "Level 25 Crypt",
    "chest": "Infernal Chest",
    "score": 550
  },
  {
    "player": "GM Maximus",
    "source": "Level 25 Crypt",
    "chest": "Bone Chest",
    "score": 550
  },
  {
    "player": "GM Maximus",
    "source": "Level 25 Crypt",
    "chest": "Gnome Workshop Chest",
    "score": 550
  },
  {
    "player": "GM Maximus",
    "source": "Level 20 Crypt",
    "chest": "Sand Chest",
    "score": 167
  },
  {
    "player": "GM Maximus",
    "source": "Level 20 Crypt",
    "chest": "Elegant Chest",
    "score": 167
  },
  {
    "player": "GM Maximus",
    "source": "Level 25 epic Crypt",
    "chest": "Trillium Chest",
    "score": 1000
  },
  {
    "player": "GM Maximus",
    "source": "Level 20 Crypt",
    "chest": "Forgotten Chest",
    "score": 167
  },
  {
    "player": "GM Maximus",
    "source": "Level 25 epic Crypt",
    "chest": "Braided Chest",
    "score": 1000
  },
  {
    "player": "GM Maximus",
    "source": "Level 25 Crypt",
    "chest": "Orc Chest",
    "score": 550
  },
  {
    "player": "GM Maximus",
    "source": "Level 25 Crypt",
    "chest": "Forgotten Chest",
    "score": 550
  },
  {
    "player": "GM Maximus",
    "source": "Level 20 Crypt",
    "chest": "Cobra Chest",
    "score": 167
  },
  {
    "player": "GM Maximus",
    "source": "Level 25 Crypt",
    "chest": "Bone Chest",
    "score": 550
  },
  {
    "player": "GM Maximus",
    "source": "Level 25 Crypt",
    "chest": "Barbarian Chest",
    "score": 550
  },
  {
    "player": "GM Maximus",
    "source": "Level 25 Crypt",
    "chest": "Cobra Chest",
    "score": 550
  },
  {
    "player": "GM Maximus",
    "source": "Level 25 Crypt",
    "chest": "Stone Chest",
    "score": 550
  },
  {
    "player": "GM Maximus",
    "source": "Level 25 Crypt",
    "chest": "Barbarian Chest",
    "score": 550
  },
  {
    "player": "Artemis",
    "source": "Level 10 Crypt",
    "chest": "Gnome Workshop Chest",
    "score": 35
  },
  {
    "player": "Moondragon",
    "source": "Level 15 Crypt",
    "chest": "Gnome Workshop Chest",
    "score": 75
  },
  {
    "player": "Moondragon",
    "source": "Level 5 Crypt",
    "chest": "Forgotten Chest",
    "score": 13
  },
  {
    "player": "Moondragon",
    "source": "Level 15 Crypt",
    "chest": "Orc Chest",
    "score": 75
  },
  {
    "player": "Moondragon",
    "source": "Level 25 epic Crypt",
    "chest": "Scarab Chest",
    "score": 1000
  },
  {
    "player": "Moondragon",
    "source": "Level 25 rare Crypt",
    "chest": "Rare Dragon Chest",
    "score": 800
  },
  {
    "player": "Burus",
    "source": "Level 30 epic Crypt",
    "chest": "House of Horrors Chest",
    "score": 1184
  },
  {
    "player": "SANGEETA",
    "source": "Level 15 Crypt",
    "chest": "Stone Chest",
    "score": 75
  },
  {
    "player": "SANGEETA",
    "source": "Level 15 Crypt",
    "chest": "Fire Chest",
    "score": 75
  },
  {
    "player": "SANGEETA",
    "source": "Level 10 Crypt",
    "chest": "Mayan Chest",
    "score": 35
  },
  {
    "player": "SBD",
    "source": "Level 10 Crypt",
    "chest": "Sand Chest",
    "score": 35
  },
  {
    "player": "SANGEETA",
    "source": "Level 25 rare Crypt",
    "chest": "Rare Dragon Chest",
    "score": 800
  },
  {
    "player": "Burus",
    "source": "Level 15 Crypt",
    "chest": "Barbarian Chest",
    "score": 75
  },
  {
    "player": "Burus",
    "source": "Level 20 Crypt",
    "chest": "Stone Chest",
    "score": 167
  },
  {
    "player": "Burus",
    "source": "Level 20 Crypt",
    "chest": "Elegant Chest",
    "score": 167
  },
  {
    "player": "SANGEETA",
    "source": "Level 25 rare Crypt",
    "chest": "Rare Dragon Chest",
    "score": 800
  },
  {
    "player": "Tygrallador",
    "source": "Level 15 Crypt",
    "chest": "Mayan Chest",
    "score": 75
  },
  {
    "player": "Tygrallador",
    "source": "Level 15 Crypt",
    "chest": "Gnome Workshop Chest",
    "score": 75
  },
  {
    "player": "Tygrallador",
    "source": "Level 15 Crypt",
    "chest": "Fire Chest",
    "score": 75
  },
  {
    "player": "Kratos",
    "source": "Level 20 Crypt",
    "chest": "Elegant Chest",
    "score": 167
  },
  {
    "player": "Kratos",
    "source": "Level 20 Crypt",
    "chest": "Gnome Workshop Chest",
    "score": 167
  },
  {
    "player": "Kratos",
    "source": "Level 20 Crypt",
    "chest": "Gnome Workshop Chest",
    "score": 167
  },
  {
    "player": "Kratos",
    "source": "Level 20 Crypt",
    "chest": "Barbarian Chest",
    "score": 167
  },
  {
    "player": "Kratos",
    "source": "Level 20 Crypt",
    "chest": "Cobra Chest",
    "score": 167
  },
  {
    "player": "Kratos",
    "source": "Level 20 Crypt",
    "chest": "Bone Chest",
    "score": 167
  },
  {
    "player": "Kratos",
    "source": "Level 20 rare Crypt",
    "chest": "Rare Dragon Chest",
    "score": 319
  },
  {
    "player": "Kratos",
    "source": "Level 20 rare Crypt",
    "chest": "Rare Dragon Chest",
    "score": 319
  },
  {
    "player": "Kratos",
    "source": "Level 20 epic Crypt",
    "chest": "Ancient Warrior's Chest",
    "score": 598
  },
  {
    "player": "Kratos",
    "source": "Level 20 epic Crypt",
    "chest": "Turtle Chest",
    "score": 598
  },
  {
    "player": "Beanara",
    "source": "Level 20 epic Crypt",
    "chest": "Braided Chest",
    "score": 598
  },
  {
    "player": "Beanara",
    "source": "Level 20 epic Crypt",
    "chest": "Minotaur Chest",
    "score": 598
  },
  {
    "player": "Geel",
    "source": "Level 10 Crypt",
    "chest": "Forgotten Chest",
    "score": 35
  },
  {
    "player": "Beanara",
    "source": "Level 10 Crypt",
    "chest": "Bone Chest",
    "score": 35
  },
  {
    "player": "Beanara",
    "source": "Level 20 rare Crypt",
    "chest": "Rare Dragon Chest",
    "score": 319
  },
  {
    "player": "Malang",
    "source": "Level 20 Crypt",
    "chest": "Barbarian Chest",
    "score": 167
  },
  {
    "player": "Beanara",
    "source": "Level 20 rare Crypt",
    "chest": "Rare Dragon Chest",
    "score": 319
  },
  {
    "player": "Beanara",
    "source": "Level 20 epic Crypt",
    "chest": "Scarab Chest",
    "score": 598
  },
  {
    "player": "Atlantis II",
    "source": "Level 25 Crypt",
    "chest": "Bone Chest",
    "score": 550
  },
  {
    "player": "Atlantis II",
    "source": "Level 25 Crypt",
    "chest": "Cobra Chest",
    "score": 550
  },
  {
    "player": "Atlantis II",
    "source": "Level 15 Crypt",
    "chest": "Cobra Chest",
    "score": 75
  },
  {
    "player": "Atlantis II",
    "source": "Arena",
    "chest": "Gladiator's Chest",
    "score": 30
  },
  {
    "player": "Moondragon",
    "source": "Level 25 epic Crypt",
    "chest": "Cobalt Chest",
    "score": 1000
  },
  {
    "player": "Moondragon",
    "source": "Level 30 rare Crypt",
    "chest": "Rare Dragon Chest",
    "score": 1200
  },
  {
    "player": "Conjulas",
    "source": "Level 10 Crypt",
    "chest": "Sand Chest",
    "score": 35
  },
  {
    "player": "Nakoma",
    "source": "Level 15 Crypt",
    "chest": "Forgotten Chest",
    "score": 75
  },
  {
    "player": "Nakoma",
    "source": "Level 15 Crypt",
    "chest": "Barbarian Chest",
    "score": 75
  },
  {
    "player": "Nakoma",
    "source": "Level 15 epic Crypt",
    "chest": "Scorpion Chest",
    "score": 308
  },
  {
    "player": "Naong",
    "source": "Level 35 epic Crypt",
    "chest": "Trillium Chest",
    "score": 1480
  },
  {
    "player": "Naong",
    "source": "Level 10 rare Crypt",
    "chest": "Rare Dragon Chest",
    "score": 66
  },
  {
    "player": "Naong",
    "source": "Level 30 rare Crypt",
    "chest": "Rare Dragon Chest",
    "score": 1200
  },
  {
    "player": "Naong",
    "source": "Level 10 rare Crypt",
    "chest": "Rare Dragon Chest",
    "score": 66
  },
  {
    "player": "Nakoma",
    "source": "Level 15 epic Crypt",
    "chest": "Titansteel Chest",
    "score": 308
  },
  {
    "player": "Naong",
    "source": "Level 25 rare Crypt",
    "chest": "Rare Dragon Chest",
    "score": 800
  },
  {
    "player": "Naong",
    "source": "Level 30 rare Crypt",
    "chest": "Rare Dragon Chest",
    "score": 1200
  },
  {
    "player": "Nakoma",
    "source": "Level 15 epic Crypt",
    "chest": "Braided Chest",
    "score": 308
  },
  {
    "player": "Naong",
    "source": "Level 20 Crypt",
    "chest": "Sand Chest",
    "score": 167
  },
  {
    "player": "Nakoma",
    "source": "Level 15 epic Crypt",
    "chest": "Cobalt Chest",
    "score": 308
  },
  {
    "player": "Naong",
    "source": "Level 15 Crypt",
    "chest": "Bone Chest",
    "score": 75
  },
  {
    "player": "Naong",
    "source": "Level 20 Crypt",
    "chest": "Mayan Chest",
    "score": 167
  },
  {
    "player": "Naong",
    "source": "Level 10 Crypt",
    "chest": "Sand Chest",
    "score": 35
  },
  {
    "player": "Nakoma",
    "source": "Level 15 Crypt",
    "chest": "Barbarian Chest",
    "score": 75
  },
  {
    "player": "Naong",
    "source": "Level 15 Crypt",
    "chest": "Orc Chest",
    "score": 75
  },
  {
    "player": "Naong",
    "source": "Level 10 Crypt",
    "chest": "Elegant Chest",
    "score": 35
  },
  {
    "player": "Naong",
    "source": "Level 15 Crypt",
    "chest": "Forgotten Chest",
    "score": 75
  },
  {
    "player": "Naong",
    "source": "Level 25 Crypt",
    "chest": "Elegant Chest",
    "score": 550
  },
  {
    "player": "Naong",
    "source": "Level 15 Crypt",
    "chest": "Infernal Chest",
    "score": 75
  },
  {
    "player": "Naong",
    "source": "Level 20 Crypt",
    "chest": "Orc Chest",
    "score": 167
  },
  {
    "player": "Naong",
    "source": "Level 15 Crypt",
    "chest": "Forgotten Chest",
    "score": 75
  },
  {
    "player": "Naong",
    "source": "Level 20 Crypt",
    "chest": "Elegant Chest",
    "score": 167
  },
  {
    "player": "Naong",
    "source": "Level 20 Crypt",
    "chest": "Cobra Chest",
    "score": 167
  },
  {
    "player": "Naong",
    "source": "Level 10 Crypt",
    "chest": "Orc Chest",
    "score": 35
  },
  {
    "player": "Naong",
    "source": "Level 15 Crypt",
    "chest": "Elegant Chest",
    "score": 75
  },
  {
    "player": "Naong",
    "source": "Level 20 Crypt",
    "chest": "Orc Chest",
    "score": 167
  },
  {
    "player": "Naong",
    "source": "Level 15 Crypt",
    "chest": "Infernal Chest",
    "score": 75
  },
  {
    "player": "Naong",
    "source": "Level 10 Crypt",
    "chest": "Forgotten Chest",
    "score": 35
  },
  {
    "player": "Naong",
    "source": "Level 20 Crypt",
    "chest": "Sand Chest",
    "score": 167
  },
  {
    "player": "Naong",
    "source": "Level 10 Crypt",
    "chest": "Bone Chest",
    "score": 35
  },
  {
    "player": "Naong",
    "source": "Level 10 Crypt",
    "chest": "Sand Chest",
    "score": 35
  },
  {
    "player": "Naong",
    "source": "Level 20 Crypt",
    "chest": "Elegant Chest",
    "score": 167
  },
  {
    "player": "Naong",
    "source": "Level 15 Crypt",
    "chest": "Mayan Chest",
    "score": 75
  },
  {
    "player": "Naong",
    "source": "Level 15 Crypt",
    "chest": "Fire Chest",
    "score": 75
  },
  {
    "player": "Naong",
    "source": "Level 25 Crypt",
    "chest": "Barbarian Chest",
    "score": 550
  },
  {
    "player": "Naong",
    "source": "Level 20 Crypt",
    "chest": "Mayan Chest",
    "score": 167
  },
  {
    "player": "Naong",
    "source": "Level 15 Crypt",
    "chest": "Bone Chest",
    "score": 75
  },
  {
    "player": "Naong",
    "source": "Level 10 Crypt",
    "chest": "Orc Chest",
    "score": 35
  },
  {
    "player": "Naong",
    "source": "Level 15 Crypt",
    "chest": "Bone Chest",
    "score": 75
  },
  {
    "player": "Naong",
    "source": "Level 20 Crypt",
    "chest": "Cobra Chest",
    "score": 167
  },
  {
    "player": "Naong",
    "source": "Level 10 Crypt",
    "chest": "Fire Chest",
    "score": 35
  },
  {
    "player": "Naong",
    "source": "Level 10 Crypt",
    "chest": "Bone Chest",
    "score": 35
  },
  {
    "player": "Naong",
    "source": "Level 20 Crypt",
    "chest": "Fire Chest",
    "score": 167
  },
  {
    "player": "Naong",
    "source": "Level 10 Crypt",
    "chest": "Sand Chest",
    "score": 35
  },
  {
    "player": "Naong",
    "source": "Level 10 Crypt",
    "chest": "Forgotten Chest",
    "score": 35
  },
  {
    "player": "Naong",
    "source": "Level 20 Crypt",
    "chest": "Fire Chest",
    "score": 167
  },
  {
    "player": "Naong",
    "source": "Level 15 Crypt",
    "chest": "Cobra Chest",
    "score": 75
  },
  {
    "player": "Naong",
    "source": "Level 10 Crypt",
    "chest": "Mayan Chest",
    "score": 35
  },
  {
    "player": "Naong",
    "source": "Level 25 Crypt",
    "chest": "Cobra Chest",
    "score": 550
  },
  {
    "player": "Naong",
    "source": "Level 20 Crypt",
    "chest": "Elegant Chest",
    "score": 167
  },
  {
    "player": "Naong",
    "source": "Level 10 Crypt",
    "chest": "Orc Chest",
    "score": 35
  },
  {
    "player": "Naong",
    "source": "Level 20 Crypt",
    "chest": "Barbarian Chest",
    "score": 167
  },
  {
    "player": "Naong",
    "source": "Level 10 Crypt",
    "chest": "Orc Chest",
    "score": 35
  },
  {
    "player": "Naong",
    "source": "Level 25 Crypt",
    "chest": "Cobra Chest",
    "score": 550
  },
  {
    "player": "Naong",
    "source": "Level 20 Crypt",
    "chest": "Bone Chest",
    "score": 167
  },
  {
    "player": "Naong",
    "source": "Level 20 Crypt",
    "chest": "Sand Chest",
    "score": 167
  },
  {
    "player": "MACIEJ",
    "source": "Arena",
    "chest": "Gladiator's Chest",
    "score": 30
  },
  {
    "player": "MACIEJ",
    "source": "Level 25 Crypt",
    "chest": "Orc Chest",
    "score": 550
  },
  {
    "player": "MACIEJ",
    "source": "Level 20 Crypt",
    "chest": "Orc Chest",
    "score": 167
  },
  {
    "player": "SBD",
    "source": "Level 15 Crypt",
    "chest": "Infernal Chest",
    "score": 75
  },
  {
    "player": "MACIEJ",
    "source": "Level 20 Crypt",
    "chest": "Orc Chest",
    "score": 167
  },
  {
    "player": "SANGEETA",
    "source": "Clan wealth",
    "chest": "Common Chest of Wealth",
    "score": 0
  },
  {
    "player": "SANGEETA",
    "source": "Clan wealth",
    "chest": "Uncommon Chest of Wealth",
    "score": 0
  },
  {
    "player": "SANGEETA",
    "source": "Clan wealth",
    "chest": "Rare Chest of Wealth",
    "score": 0
  },
  {
    "player": "SANGEETA",
    "source": "Clan wealth",
    "chest": "Epic Chest of Wealth",
    "score": 0
  },
  {
    "player": "island",
    "source": "Level 25 epic Crypt",
    "chest": "Chest of the Cursed",
    "score": 1000
  },
  {
    "player": "kari",
    "source": "Level 20 Crypt",
    "chest": "Orc Chest",
    "score": 167
  },
  {
    "player": "kari",
    "source": "Level 20 Crypt",
    "chest": "Infernal Chest",
    "score": 167
  },
  {
    "player": "Kratos",
    "source": "Carrot Monster",
    "chest": "Carrot Chest",
    "score": 0
  },
  {
    "player": "Eufrozyna",
    "source": "Level 20 epic Crypt",
    "chest": "Minotaur Chest",
    "score": 598
  },
  {
    "player": "AnyaSpy",
    "source": "Level 25 Crypt",
    "chest": "Gnome Workshop Chest",
    "score": 550
  },
  {
    "player": "AnyaSpy",
    "source": "Level 20 Crypt",
    "chest": "Cobra Chest",
    "score": 167
  },
  {
    "player": "AnyaSpy",
    "source": "Level 25 Crypt",
    "chest": "Fire Chest",
    "score": 550
  },
  {
    "player": "AnyaSpy",
    "source": "Level 5 Crypt",
    "chest": "Bone Chest",
    "score": 13
  },
  {
    "player": "AnyaSpy",
    "source": "Level 20 epic Crypt",
    "chest": "Scarab Chest",
    "score": 598
  },
  {
    "player": "Anubis",
    "source": "Level 20 Crypt",
    "chest": "Bone Chest",
    "score": 167
  },
  {
    "player": "Anubis",
    "source": "Level 20 epic Crypt",
    "chest": "Priest's Chest",
    "score": 598
  },
  {
    "player": "Anubis",
    "source": "Level 20 Crypt",
    "chest": "Barbarian Chest",
    "score": 167
  },
  {
    "player": "Anubis",
    "source": "Level 25 epic Crypt",
    "chest": "Scarab Chest",
    "score": 1000
  },
  {
    "player": "Anubis",
    "source": "Level 20 Crypt",
    "chest": "Elegant Chest",
    "score": 167
  },
  {
    "player": "Anubis",
    "source": "Level 25 Crypt",
    "chest": "Cobra Chest",
    "score": 550
  },
  {
    "player": "Princess Noli",
    "source": "Level 15 Crypt",
    "chest": "Mayan Chest",
    "score": 75
  },
  {
    "player": "Princess Noli",
    "source": "Level 15 Crypt",
    "chest": "Cobra Chest",
    "score": 75
  },
  {
    "player": "Princess Noli",
    "source": "Level 15 Crypt",
    "chest": "Mayan Chest",
    "score": 75
  },
  {
    "player": "Princess Noli",
    "source": "Level 15 Crypt",
    "chest": "Cobra Chest",
    "score": 75
  },
  {
    "player": "Princess Noli",
    "source": "Level 15 Crypt",
    "chest": "Cobra Chest",
    "score": 75
  },
  {
    "player": "Princess Noli",
    "source": "Level 20 Crypt",
    "chest": "Mayan Chest",
    "score": 167
  },
  {
    "player": "Princess Noli",
    "source": "Level 10 Crypt",
    "chest": "Barbarian Chest",
    "score": 35
  },
  {
    "player": "Silver",
    "source": "Level 20 Crypt",
    "chest": "Fire Chest",
    "score": 167
  },
  {
    "player": "Princess Noli",
    "source": "Level 15 rare Crypt",
    "chest": "Rare Dragon Chest",
    "score": 130
  },
  {
    "player": "Silver",
    "source": "Level 20 Crypt",
    "chest": "Fire Chest",
    "score": 167
  },
  {
    "player": "Silver",
    "source": "Level 20 Crypt",
    "chest": "Fire Chest",
    "score": 167
  },
  {
    "player": "Linfiren",
    "source": "Arena",
    "chest": "Gladiator's Chest",
    "score": 30
  },
  {
    "player": "Silver",
    "source": "Level 20 Crypt",
    "chest": "Fire Chest",
    "score": 167
  },
  {
    "player": "Princess Noli",
    "source": "Level 15 Crypt",
    "chest": "Barbarian Chest",
    "score": 75
  },
  {
    "player": "Silver",
    "source": "Level 20 Crypt",
    "chest": "Fire Chest",
    "score": 167
  },
  {
    "player": "Princess Noli",
    "source": "Level 15 Crypt",
    "chest": "Cobra Chest",
    "score": 75
  },
  {
    "player": "Silver",
    "source": "Level 20 Crypt",
    "chest": "Fire Chest",
    "score": 167
  },
  {
    "player": "Silver",
    "source": "Level 20 epic Crypt",
    "chest": "Cobalt Chest",
    "score": 598
  },
  {
    "player": "Silver",
    "source": "Level 20 epic Crypt",
    "chest": "Cobalt Chest",
    "score": 598
  },
  {
    "player": "Silver",
    "source": "Level 20 rare Crypt",
    "chest": "Rare Dragon Chest",
    "score": 319
  },
  {
    "player": "Silver",
    "source": "Level 20 rare Crypt",
    "chest": "Rare Dragon Chest",
    "score": 319
  },
  {
    "player": "DuzyCharlie",
    "source": "Level 20 Crypt",
    "chest": "Stone Chest",
    "score": 167
  },
  {
    "player": "Gesa",
    "source": "Level 15 Crypt",
    "chest": "Stone Chest",
    "score": 75
  },
  {
    "player": "Gesa",
    "source": "Level 15 Crypt",
    "chest": "Cobra Chest",
    "score": 75
  },
  {
    "player": "DuzyCharlie",
    "source": "Level 20 Crypt",
    "chest": "Gnome Workshop Chest",
    "score": 167
  },
  {
    "player": "Salka",
    "source": "Level 17 heroic Monster",
    "chest": "Elven Chest",
    "score": 110
  },
  {
    "player": "Salka",
    "source": "Level 17 heroic Monster",
    "chest": "Elven Chest",
    "score": 110
  },
  {
    "player": "Naong",
    "source": "Level 25 Crypt",
    "chest": "Cobra Chest",
    "score": 550
  },
  {
    "player": "Naong",
    "source": "Level 25 Crypt",
    "chest": "Cobra Chest",
    "score": 550
  },
  {
    "player": "Naong",
    "source": "Level 25 Crypt",
    "chest": "Elegant Chest",
    "score": 550
  },
  {
    "player": "Naong",
    "source": "Level 25 Crypt",
    "chest": "Cobra Chest",
    "score": 550
  },
  {
    "player": "Naong",
    "source": "Level 25 Crypt",
    "chest": "Orc Chest",
    "score": 550
  },
  {
    "player": "Naong",
    "source": "Level 25 Crypt",
    "chest": "Elegant Chest",
    "score": 550
  },
  {
    "player": "Naong",
    "source": "Level 25 Crypt",
    "chest": "Cobra Chest",
    "score": 550
  },
  {
    "player": "Naong",
    "source": "Level 25 Crypt",
    "chest": "Cobra Chest",
    "score": 550
  },
  {
    "player": "Naong",
    "source": "Level 25 Crypt",
    "chest": "Fire Chest",
    "score": 550
  },
  {
    "player": "Naong",
    "source": "Level 25 Crypt",
    "chest": "Fire Chest",
    "score": 550
  },
  {
    "player": "McGeyerver",
    "source": "Level 5 Crypt",
    "chest": "Bone Chest",
    "score": 13
  },
  {
    "player": "Princess Noli",
    "source": "Level 15 rare Crypt",
    "chest": "Rare Dragon Chest",
    "score": 130
  },
  {
    "player": "Princess Noli",
    "source": "Level 15 Crypt",
    "chest": "Mayan Chest",
    "score": 75
  },
  {
    "player": "Princess Noli",
    "source": "Level 15 Crypt",
    "chest": "Barbarian Chest",
    "score": 75
  },
  {
    "player": "Cid Campeador",
    "source": "Level 15 epic Crypt",
    "chest": "Barbarian Chest",
    "score": 308
  },
  {
    "player": "Cid Campeador",
    "source": "Level 15 Crypt",
    "chest": "Cobra Chest",
    "score": 75
  },
  {
    "player": "Princess Noli",
    "source": "Level 20 Crypt",
    "chest": "Barbarian Chest",
    "score": 167
  },
  {
    "player": "Cid Campeador",
    "source": "Level 20 Crypt",
    "chest": "Sand Chest",
    "score": 167
  },
  {
    "player": "Princess Noli",
    "source": "Level 15 Crypt",
    "chest": "Mayan Chest",
    "score": 75
  },
  {
    "player": "Salka",
    "source": "Level 20 Citadel",
    "chest": "Elven Citadel Chest",
    "score": 50
  },
  {
    "player": "Cid Campeador",
    "source": "Level 15 Crypt",
    "chest": "Infernal Chest",
    "score": 75
  },
  {
    "player": "Princess Noli",
    "source": "Level 5 Crypt",
    "chest": "Barbarian Chest",
    "score": 13
  },
  {
    "player": "Princess Noli",
    "source": "Level 5 Crypt",
    "chest": "Cobra Chest",
    "score": 13
  },
  {
    "player": "Princess Noli",
    "source": "Level 5 Crypt",
    "chest": "IE ~ | Mayan Chest",
    "score": 13
  },
  {
    "player": "GM Maximus",
    "source": "Level 20 Crypt",
    "chest": "Orc Chest",
    "score": 167
  },
  {
    "player": "GM Maximus",
    "source": "Level 20 Crypt",
    "chest": "Gnome Workshop Chest",
    "score": 167
  },
  {
    "player": "GM Maximus",
    "source": "Level 20 Crypt",
    "chest": "Forgotten Chest",
    "score": 167
  },
  {
    "player": "GM Maximus",
    "source": "Level 20 Crypt",
    "chest": "Stone Chest",
    "score": 167
  },
  {
    "player": "Princess Noli",
    "source": "Level 10 Crypt",
    "chest": "Elegant Chest",
    "score": 35
  },
  {
    "player": "Princess Noli",
    "source": "Level 15 Crypt",
    "chest": "Cobra Chest",
    "score": 75
  },
  {
    "player": "Princess Noli",
    "source": "Level 5 Crypt",
    "chest": "Elegant Chest",
    "score": 13
  },
  {
    "player": "Cid Campeador",
    "source": "Level 20 Crypt",
    "chest": "Barbarian Chest",
    "score": 167
  },
  {
    "player": "GM Maximus",
    "source": "Level 20 Crypt",
    "chest": "Gnome Workshop Chest",
    "score": 167
  },
  {
    "player": "GM Maximus",
    "source": "Level 20 Crypt",
    "chest": "Stone Chest",
    "score": 167
  },
  {
    "player": "GM Maximus",
    "source": "Level 25 Crypt",
    "chest": "Stone Chest",
    "score": 550
  },
  {
    "player": "GM Maximus",
    "source": "Level 20 Crypt",
    "chest": "Stone Chest",
    "score": 167
  },
  {
    "player": "GM Maximus",
    "source": "Level 25 Crypt",
    "chest": "Bone Chest",
    "score": 550
  },
  {
    "player": "GM Maximus",
    "source": "Level 25 Crypt",
    "chest": "Stone Chest",
    "score": 550
  },
  {
    "player": "TS Baran",
    "source": "Level 25 epic Crypt",
    "chest": "Priest's Chest",
    "score": 1000
  },
  {
    "player": "GM Maximus",
    "source": "Level 20 Crypt",
    "chest": "Gnome Workshop Chest",
    "score": 167
  },
  {
    "player": "Princess Noli",
    "source": "Level 15 Crypt",
    "chest": "Elegant Chest",
    "score": 75
  },
  {
    "player": "Princess Noli",
    "source": "Level 15 Crypt",
    "chest": "Cobra Chest",
    "score": 75
  },
  {
    "player": "GM Maximus",
    "source": "Level 20 epic Crypt",
    "chest": "Priest's Chest",
    "score": 598
  },
  {
    "player": "GM Maximus",
    "source": "Level 30 epic Crypt",
    "chest": "House of Horrors Chest",
    "score": 1184
  },
  {
    "player": "GM Maximus",
    "source": "Level 25 epic Crypt",
    "chest": "House of Horrors Chest",
    "score": 1000
  },
  {
    "player": "GM Maximus",
    "source": "Level 25 rare Crypt",
    "chest": "Rare Dragon Chest",
    "score": 800
  },
  {
    "player": "Salka",
    "source": "Level 20 Citadel",
    "chest": "Elven Citadel Chest",
    "score": 50
  },
  {
    "player": "GM Maximus",
    "source": "Level 25 rare Crypt",
    "chest": "Rare Dragon Chest",
    "score": 800
  },
  {
    "player": "GM Maximus",
    "source": "Level 25 rare Crypt",
    "chest": "Rare Dragon Chest",
    "score": 800
  },
  {
    "player": "TS Baran",
    "source": "Level 25 epic Crypt",
    "chest": "Cobalt Chest",
    "score": 1000
  },
  {
    "player": "TS Baran",
    "source": "Level 25 Crypt",
    "chest": "Fire Chest",
    "score": 550
  },
  {
    "player": "TS Baran",
    "source": "Level 25 Crypt",
    "chest": "Barbarian Chest",
    "score": 550
  },
  {
    "player": "TS Baran",
    "source": "Level 25 Crypt",
    "chest": "Sand Chest",
    "score": 550
  },
  {
    "player": "Salka",
    "source": "Level 20 Citadel",
    "chest": "Elven Citadel Chest",
    "score": 50
  },
  {
    "player": "TS Baran",
    "source": "Level 30 rare Crypt",
    "chest": "Rare Dragon Chest",
    "score": 1200
  },
  {
    "player": "TS Baran",
    "source": "Level 30 epic Crypt",
    "chest": "Cobalt Chest",
    "score": 1184
  },
  {
    "player": "GM Maximus",
    "source": "Level 15 epic Crypt",
    "chest": "Abandoned Chest",
    "score": 308
  },
  {
    "player": "TS Baran",
    "source": "Level 30 epic Crypt",
    "chest": "Minotaur Chest",
    "score": 1184
  },
  {
    "player": "GM Maximus",
    "source": "Level 20 epic Crypt",
    "chest": "Braided Chest",
    "score": 598
  },
  {
    "player": "GM Maximus",
    "source": "Level 15 epic Crypt",
    "chest": "Harpy Chest",
    "score": 308
  },
  {
    "player": "TS Baran",
    "source": "Level 30 epic Crypt",
    "chest": "Trillium Chest",
    "score": 1184
  },
  {
    "player": "GM Maximus",
    "source": "Level 20 epic Crypt",
    "chest": "Cobalt Chest",
    "score": 598
  },
  {
    "player": "TS Baran",
    "source": "Level 30 rare Crypt",
    "chest": "Rare Dragon Chest",
    "score": 1200
  },
  {
    "player": "GM Maximus",
    "source": "Level 20 epic Crypt",
    "chest": "Scarab Chest",
    "score": 598
  },
  {
    "player": "TS Baran",
    "source": "Level 30 rare Crypt",
    "chest": "Rare Dragon Chest",
    "score": 1200
  },
  {
    "player": "GM Maximus",
    "source": "Level 20 epic Crypt",
    "chest": "Scarab Chest",
    "score": 598
  },
  {
    "player": "GM Maximus",
    "source": "Level 20 epic Crypt",
    "chest": "Harpy Chest",
    "score": 598
  },
  {
    "player": "TS Baran",
    "source": "Level 30 rare Crypt",
    "chest": "Rare Dragon Chest",
    "score": 1200
  },
  {
    "player": "GM Maximus",
    "source": "Level 20 epic Crypt",
    "chest": "Scorpion Chest",
    "score": 598
  },
  {
    "player": "TS Baran",
    "source": "Level 25 Crypt",
    "chest": "Mayan Chest",
    "score": 550
  },
  {
    "player": "Dire Wolf",
    "source": "Level 35 epic Crypt",
    "chest": "REAL",
    "score": 1480
  },
  {
    "player": "Dire Wolf",
    "source": "Level 25 Crypt",
    "chest": "Fire Chest",
    "score": 550
  },
  {
    "player": "Dire Wolf",
    "source": "Level 25 Crypt",
    "chest": "Fire Chest",
    "score": 550
  },
  {
    "player": "Dire Wolf",
    "source": "Level 25 Crypt",
    "chest": "Fire Chest",
    "score": 550
  },
  {
    "player": "Dire Wolf",
    "source": "Level 25 Crypt",
    "chest": "Fire Chest",
    "score": 550
  },
  {
    "player": "Dire Wolf",
    "source": "Level 25 Crypt",
    "chest": "Fire Chest",
    "score": 550
  },
  {
    "player": "Salka",
    "source": "Level 20 Citadel",
    "chest": "Elven Citadel Chest",
    "score": 50
  },
  {
    "player": "Dire Wolf",
    "source": "Level 25 Crypt",
    "chest": "Fire Chest",
    "score": 550
  },
  {
    "player": "Dire Wolf",
    "source": "Level 25 Crypt",
    "chest": "Fire Chest",
    "score": 550
  },
  {
    "player": "Dire Wolf",
    "source": "Level 25 Crypt",
    "chest": "Fire Chest",
    "score": 550
  },
  {
    "player": "Gesa",
    "source": "Level 15 Crypt",
    "chest": "Forgotten Chest",
    "score": 75
  },
  {
    "player": "Gesa",
    "source": "Level 10 Crypt",
    "chest": "Bone Chest",
    "score": 35
  },
  {
    "player": "Gesa",
    "source": "Level 15 Crypt",
    "chest": "Mayan Chest",
    "score": 75
  },
  {
    "player": "Gesa",
    "source": "Level 25 rare Crypt",
    "chest": "Rare Dragon Chest",
    "score": 800
  },
  {
    "player": "Gesa",
    "source": "Level 15 epic Crypt",
    "chest": "Cobalt Chest",
    "score": 308
  },
  {
    "player": "Gesa",
    "source": "Level 15 epic Crypt",
    "chest": "Ancient Warrior's Chest",
    "score": 308
  },
  {
    "player": "Gesa",
    "source": "Level 15 epic Crypt",
    "chest": "Priest's Chest",
    "score": 308
  },
  {
    "player": "Gesa",
    "source": "Level 15 epic Crypt",
    "chest": "Trillium Chest",
    "score": 308
  },
  {
    "player": "Gesa",
    "source": "Level 15 epic Crypt",
    "chest": "Cobalt Chest",
    "score": 308
  },
  {
    "player": "Atlantis II",
    "source": "Level 25 epic Crypt",
    "chest": "[clam SH) Trillium Chest",
    "score": 1000
  },
  {
    "player": "Princess Noli",
    "source": "Level 15 rare Crypt",
    "chest": "Rare Dragon Chest",
    "score": 130
  },
  {
    "player": "Princess Noli",
    "source": "Level 10 Crypt",
    "chest": "Elegant Chest",
    "score": 35
  },
  {
    "player": "Princess Noli",
    "source": "Level 10 Crypt",
    "chest": "Cobra Chest",
    "score": 35
  },
  {
    "player": "Princess Noli",
    "source": "Level 15 Crypt",
    "chest": "Cobra Chest",
    "score": 75
  },
  {
    "player": "Princess Noli",
    "source": "Level 10 Crypt",
    "chest": "Cobra Chest",
    "score": 35
  },
  {
    "player": "SüLocann 171",
    "source": "Level 15 rare Crypt",
    "chest": "Rare Dragon Chest",
    "score": 130
  },
  {
    "player": "SüLocann 171",
    "source": "Level 20 Crypt",
    "chest": "Fire Chest",
    "score": 167
  },
  {
    "player": "Cpt Chaos",
    "source": "Level 20 rare Crypt",
    "chest": "Rare Dragon Chest",
    "score": 319
  },
  {
    "player": "Dingo Kaneef",
    "source": "Level 30 rare Crypt",
    "chest": "Rare Dragon Chest",
    "score": 1200
  },
  {
    "player": "Dingo Kaneef",
    "source": "Level 30 rare Crypt",
    "chest": "Rare Dragon Chest",
    "score": 1200
  },
  {
    "player": "Dingo Kaneef",
    "source": "Level 25 Crypt",
    "chest": "Orc Chest",
    "score": 550
  },
  {
    "player": "Dingo Kaneef",
    "source": "Level 25 Crypt",
    "chest": "Orc Chest",
    "score": 550
  },
  {
    "player": "Dingo Kaneef",
    "source": "Level 25 Crypt",
    "chest": "Orc Chest",
    "score": 550
  },
  {
    "player": "Linfiren",
    "source": "Level 15 Crypt",
    "chest": "Cobra Chest",
    "score": 75
  },
  {
    "player": "Dingo Kaneef",
    "source": "Level 25 Crypt",
    "chest": "Mayan Chest",
    "score": 550
  },
  {
    "player": "Dingo Kaneef",
    "source": "Level 25 Crypt",
    "chest": "Barbarian Chest",
    "score": 550
  },
  {
    "player": "Linfiren",
    "source": "Level 10 Crypt",
    "chest": "Infernal Chest",
    "score": 35
  },
  {
    "player": "Linfiren",
    "source": "Level 25 Citadel",
    "chest": "Cursed Citadel Chest",
    "score": 120
  },
  {
    "player": "Pipper",
    "source": "Arena",
    "chest": "Gladiator's Chest",
    "score": 30
  },
  {
    "player": "Pipper",
    "source": "Level 25 rare Crypt",
    "chest": "Rare Dragon Chest",
    "score": 800
  },
  {
    "player": "Anubis",
    "source": "Level 10 Citadel",
    "chest": "Elven Citadel Chest",
    "score": 18
  },
  {
    "player": "Pipper",
    "source": "Level 25 Crypt",
    "chest": "Infernal Chest",
    "score": 550
  },
  {
    "player": "Pipper",
    "source": "Level 20 Crypt",
    "chest": "Orc Chest",
    "score": 167
  },
  {
    "player": "Pipper",
    "source": "Level 25 rare Crypt",
    "chest": "Rare Dragon Chest",
    "score": 800
  },
  {
    "player": "Pipper",
    "source": "Level 25 Crypt",
    "chest": "Orc Chest",
    "score": 550
  },
  {
    "player": "Pipper",
    "source": "Level 25 Crypt",
    "chest": "Mayan Chest",
    "score": 550
  },
  {
    "player": "Pipper",
    "source": "Level 25 Crypt",
    "chest": "Cobra Chest",
    "score": 550
  },
  {
    "player": "Pipper",
    "source": "Level 25 Crypt",
    "chest": "Elegant Chest",
    "score": 550
  },
  {
    "player": "Pipper",
    "source": "Level 25 rare Crypt",
    "chest": "Rare Dragon Chest",
    "score": 800
  },
  {
    "player": "Pipper",
    "source": "Level 25 rare Crypt",
    "chest": "Rare Dragon Chest",
    "score": 800
  },
  {
    "player": "Pipper",
    "source": "Level 25 rare Crypt",
    "chest": "Rare Dragon Chest",
    "score": 800
  },
  {
    "player": "Pipper",
    "source": "Level 25 epic Crypt",
    "chest": "‘G SH) Trillium Chest",
    "score": 1000
  },
  {
    "player": "Pipper",
    "source": "Level 25 epic Crypt",
    "chest": "Cobalt Chest",
    "score": 1000
  },
  {
    "player": "Pipper",
    "source": "Level 25 epic Crypt",
    "chest": "Cobalt Chest",
    "score": 1000
  },
  {
    "player": "Pipper",
    "source": "Level 25 epic Crypt",
    "chest": "Barbarian Chest",
    "score": 1000
  },
  {
    "player": "Pipper",
    "source": "Level 30 epic Crypt",
    "chest": "Harpy Chest",
    "score": 1184
  },
  {
    "player": "Dingo Kaneef",
    "source": "Carrot Monster",
    "chest": "Carrot Chest",
    "score": 0
  },
  {
    "player": "Pipper",
    "source": "Level 35 epic Crypt",
    "chest": "Scarab Chest",
    "score": 1480
  },
  {
    "player": "Linfiren",
    "source": "Level 20 rare Crypt",
    "chest": "Rare Dragon Chest",
    "score": 319
  },
  {
    "player": "Pipper",
    "source": "Level 25 epic Crypt",
    "chest": "Ancient Warrior's Chest",
    "score": 1000
  },
  {
    "player": "Pipper",
    "source": "Level 20 rare Crypt",
    "chest": "Rare Dragon Chest",
    "score": 319
  },
  {
    "player": "Pipper",
    "source": "Level 20 rare Crypt",
    "chest": "Rare Dragon Chest",
    "score": 319
  },
  {
    "player": "Pipper",
    "source": "Level 25 rare Crypt",
    "chest": "Rare Dragon Chest",
    "score": 800
  },
  {
    "player": "Pipper",
    "source": "Level 20 rare Crypt",
    "chest": "Rare Dragon Chest",
    "score": 319
  },
  {
    "player": "Pipper",
    "source": "Level 20 rare Crypt",
    "chest": "Rare Dragon Chest",
    "score": 319
  },
  {
    "player": "Pipper",
    "source": "Level 25 rare Crypt",
    "chest": "Rare Dragon Chest",
    "score": 800
  },
  {
    "player": "Salka",
    "source": "Level 20 Citadel",
    "chest": "Elven Citadel Chest",
    "score": 50
  },
  {
    "player": "Geel",
    "source": "Level 25 rare Crypt",
    "chest": "Rare Dragon Chest",
    "score": 800
  },
  {
    "player": "Anubis",
    "source": "Level 10 rare Crypt",
    "chest": "Rare Dragon Chest",
    "score": 66
  },
  {
    "player": "Geel",
    "source": "Level 25 Crypt",
    "chest": "Forgotten Chest",
    "score": 550
  },
  {
    "player": "Anubis",
    "source": "Level 10 rare Crypt",
    "chest": "Rare Dragon Chest",
    "score": 66
  },
  {
    "player": "Anubis",
    "source": "Level 15 rare Crypt",
    "chest": "Rare Dragon Chest",
    "score": 130
  },
  {
    "player": "Geel",
    "source": "Level 25 rare Crypt",
    "chest": "Rare Dragon Chest",
    "score": 800
  },
  {
    "player": "Anubis",
    "source": "Level 15 rare Crypt",
    "chest": "Rare Dragon Chest",
    "score": 130
  },
  {
    "player": "Princess Noli",
    "source": "Level 5 Crypt",
    "chest": "Cobra Chest",
    "score": 13
  },
  {
    "player": "Princess Noli",
    "source": "Level 15 rare Crypt",
    "chest": "Rare Dragon Chest",
    "score": 130
  },
  {
    "player": "Princess Noli",
    "source": "Level 15 rare Crypt",
    "chest": "Rare Dragon Chest",
    "score": 130
  },
  {
    "player": "Princess Noli",
    "source": "Level 10 Crypt",
    "chest": "Cobra Chest",
    "score": 35
  },
  {
    "player": "Princess Noli",
    "source": "Level 5 Crypt",
    "chest": "Elegant Chest",
    "score": 13
  },
  {
    "player": "Princess Noli",
    "source": "Level 15 Crypt",
    "chest": "Cobra Chest",
    "score": 75
  },
  {
    "player": "Princess Noli",
    "source": "Level 15 rare Crypt",
    "chest": "Rare Dragon Chest",
    "score": 130
  },
  {
    "player": "Princess Noli",
    "source": "Level 5 Crypt",
    "chest": "Cobra Chest",
    "score": 13
  },
  {
    "player": "Princess Noli",
    "source": "Level 20 Crypt",
    "chest": "Elegant Chest",
    "score": 167
  },
  {
    "player": "Salka",
    "source": "Level 20 Citadel",
    "chest": "Elven Citadel Chest",
    "score": 50
  },
  {
    "player": "Salka",
    "source": "Level 20 Citadel",
    "chest": "Elven Citadel Chest",
    "score": 50
  },
  {
    "player": "Arevenilas",
    "source": "Level 20 epic Crypt",
    "chest": "Chest of the Cursed",
    "score": 598
  },
  {
    "player": "Cpt Chaos",
    "source": "Level 15 Crypt",
    "chest": "Gnome Workshop Chest",
    "score": 75
  },
  {
    "player": "Ditaxe",
    "source": "Level 18 heroic Monster",
    "chest": "Cursed Chest",
    "score": 110
  },
  {
    "player": "Tygrallador",
    "source": "Level 15 Crypt",
    "chest": "Infernal Chest",
    "score": 75
  },
  {
    "player": "Tygrallador",
    "source": "Level 10 Crypt",
    "chest": "Forgotten Chest",
    "score": 35
  },
  {
    "player": "Tygrallador",
    "source": "Level 15 Crypt",
    "chest": "Bone Chest",
    "score": 75
  },
  {
    "player": "Cpt Chaos",
    "source": "Level 10 Crypt",
    "chest": "Orc Chest",
    "score": 35
  },
  {
    "player": "Tygrallador",
    "source": "Level 15 epic Crypt",
    "chest": "Turtle Chest",
    "score": 308
  },
  {
    "player": "Salka",
    "source": "Level 20 Citadel",
    "chest": "Elven Citadel Chest",
    "score": 50
  },
  {
    "player": "Cpt Chaos",
    "source": "Level 10 Crypt",
    "chest": "Gnome Workshop Chest",
    "score": 35
  },
  {
    "player": "Arevenilas",
    "source": "Level 20 epic Crypt",
    "chest": "Scorpion Chest",
    "score": 598
  },
  {
    "player": "Tygrallador",
    "source": "Level 15 Crypt",
    "chest": "Barbarian Chest",
    "score": 75
  },
  {
    "player": "Tygrallador",
    "source": "Level 10 Crypt",
    "chest": "Fire Chest",
    "score": 35
  },
  {
    "player": "Salka",
    "source": "Level 20 Citadel",
    "chest": "Elven Citadel Chest",
    "score": 50
  },
  {
    "player": "Arevenilas",
    "source": "Level 20 epic Crypt",
    "chest": "Abandoned Chest",
    "score": 598
  },
  {
    "player": "Arevenilas",
    "source": "Level 20 epic Crypt",
    "chest": "House of Horrors Chest",
    "score": 598
  },
  {
    "player": "Arevenilas",
    "source": "Level 20 epic Crypt",
    "chest": "Abandoned Chest",
    "score": 598
  },
  {
    "player": "Arevenilas",
    "source": "Level 20 epic Crypt",
    "chest": "Ancient Warrior's Chest",
    "score": 598
  },
  {
    "player": "Arevenilas",
    "source": "Level 20 epic Crypt",
    "chest": "Turtle Chest",
    "score": 598
  },
  {
    "player": "Arevenilas",
    "source": "Level 20 epic Crypt",
    "chest": "Barbarian Chest",
    "score": 598
  },
  {
    "player": "Arevenilas",
    "source": "Level 20 epic Crypt",
    "chest": "Priest's Chest",
    "score": 598
  },
  {
    "player": "SBD",
    "source": "Level 10 rare Crypt",
    "chest": "Rare Dragon Chest",
    "score": 66
  },
  {
    "player": "Linfiren",
    "source": "Level 15 Crypt",
    "chest": "Forgotten Chest",
    "score": 75
  },
  {
    "player": "Cpt Chaos",
    "source": "Level 20 Crypt",
    "chest": "Barbarian Chest",
    "score": 167
  },
  {
    "player": "Cpt Chaos",
    "source": "Level 25 Crypt",
    "chest": "Gnome Workshop Chest",
    "score": 550
  },
  {
    "player": "Cpt Chaos",
    "source": "Level 20 Crypt",
    "chest": "Forgotten Chest",
    "score": 167
  },
  {
    "player": "Cpt Chaos",
    "source": "Level 25 Crypt",
    "chest": "Sand Chest",
    "score": 550
  },
  {
    "player": "Salka",
    "source": "Level 20 Citadel",
    "chest": "Elven Citadel Chest",
    "score": 50
  },
  {
    "player": "Cpt Chaos",
    "source": "Level 20 Crypt",
    "chest": "Barbarian Chest",
    "score": 167
  },
  {
    "player": "Cpt Chaos",
    "source": "Level 20 Crypt",
    "chest": "Orc Chest",
    "score": 167
  },
  {
    "player": "Cpt Chaos",
    "source": "Level 20 Crypt",
    "chest": "Orc Chest",
    "score": 167
  },
  {
    "player": "Cpt Chaos",
    "source": "Level 20 Crypt",
    "chest": "Bone Chest",
    "score": 167
  },
  {
    "player": "Cpt Chaos",
    "source": "Level 20 Crypt",
    "chest": "Stone Chest",
    "score": 167
  },
  {
    "player": "Salka",
    "source": "Level 20 Citadel",
    "chest": "Elven Citadel Chest",
    "score": 50
  },
  {
    "player": "Cpt Chaos",
    "source": "Level 20 Crypt",
    "chest": "Mayan Chest",
    "score": 167
  },
  {
    "player": "Cpt Chaos",
    "source": "Level 20 Crypt",
    "chest": "Cobra Chest",
    "score": 167
  },
  {
    "player": "Cpt Chaos",
    "source": "Level 15 epic Crypt",
    "chest": "Scorpion Chest",
    "score": 308
  },
  {
    "player": "Cpt Chaos",
    "source": "Level 20 Crypt",
    "chest": "Bone Chest",
    "score": 167
  },
  {
    "player": "Cpt Chaos",
    "source": "Level 20 Crypt",
    "chest": "Fire Chest",
    "score": 167
  },
  {
    "player": "Cpt Chaos",
    "source": "Level 20 Crypt",
    "chest": "Bone Chest",
    "score": 167
  },
  {
    "player": "Cpt Chaos",
    "source": "Level 25 Crypt",
    "chest": "Gnome Workshop Chest",
    "score": 550
  },
  {
    "player": "Salka",
    "source": "Level 20 Citadel",
    "chest": "Elven Citadel Chest",
    "score": 50
  },
  {
    "player": "Cpt Chaos",
    "source": "Level 20 Crypt",
    "chest": "Infernal Chest",
    "score": 167
  },
  {
    "player": "Cpt Chaos",
    "source": "Level 20 Crypt",
    "chest": "Fire Chest",
    "score": 167
  },
  {
    "player": "Salka",
    "source": "Level 20 Citadel",
    "chest": "Elven Citadel Chest",
    "score": 50
  },
  {
    "player": "WraithStriker",
    "source": "Level 20 rare Crypt",
    "chest": "Rare Dragon Chest",
    "score": 319
  },
  {
    "player": "WraithStriker",
    "source": "Level 25 rare Crypt",
    "chest": "Rare Dragon Chest",
    "score": 800
  },
  {
    "player": "WraithStriker",
    "source": "Level 25 rare Crypt",
    "chest": "Rare Dragon Chest",
    "score": 800
  },
  {
    "player": "Salka",
    "source": "Level 20 Citadel",
    "chest": "Elven Citadel Chest",
    "score": 50
  },
  {
    "player": "Salka",
    "source": "Level 20 Citadel",
    "chest": "Elven Citadel Chest",
    "score": 50
  },
  {
    "player": "Salka",
    "source": "Level 20 Citadel",
    "chest": "Elven Citadel Chest",
    "score": 50
  },
  {
    "player": "Ditaxe",
    "source": "Level 20 epic Crypt",
    "chest": "Ancient Bastion Chest",
    "score": 598
  },
  {
    "player": "Ditaxe",
    "source": "Level 15 Crypt",
    "chest": "Mayan Chest",
    "score": 75
  },
  {
    "player": "Ditaxe",
    "source": "Level 20 epic Crypt",
    "chest": "Harpy Chest",
    "score": 598
  },
  {
    "player": "Ditaxe",
    "source": "Level 15 epic Crypt",
    "chest": "Barbarian Chest",
    "score": 308
  },
  {
    "player": "Ditaxe",
    "source": "Level 20 Crypt",
    "chest": "Cobra Chest",
    "score": 167
  },
  {
    "player": "Ditaxe",
    "source": "Level 15 epic Crypt",
    "chest": "Barbarian Chest",
    "score": 308
  },
  {
    "player": "Ditaxe",
    "source": "Level 15 Crypt",
    "chest": "Bone Chest",
    "score": 75
  },
  {
    "player": "Ditaxe",
    "source": "Level 15 epic Crypt",
    "chest": "Scorpion Chest",
    "score": 308
  },
  {
    "player": "Ditaxe",
    "source": "Level 25 rare Crypt",
    "chest": "Rare Dragon Chest",
    "score": 800
  },
  {
    "player": "Ditaxe",
    "source": "Level 25 Crypt",
    "chest": "Stone Chest",
    "score": 550
  },
  {
    "player": "Ditaxe",
    "source": "Level 15 Crypt",
    "chest": "Barbarian Chest",
    "score": 75
  },
  {
    "player": "Moondragon",
    "source": "Level 25 Crypt",
    "chest": "Infernal Chest",
    "score": 550
  },
  {
    "player": "Moondragon",
    "source": "Level 20 Crypt",
    "chest": "Cobra Chest",
    "score": 167
  },
  {
    "player": "Moondragon",
    "source": "Level 20 Crypt",
    "chest": "Elegant Chest",
    "score": 167
  },
  {
    "player": "Moondragon",
    "source": "Level 30 rare Crypt",
    "chest": "Rare Dragon Chest",
    "score": 1200
  },
  {
    "player": "Moondragon",
    "source": "Level 15 epic Crypt",
    "chest": "Abandoned Chest",
    "score": 308
  },
  {
    "player": "MiniAdo",
    "source": "Level 20 epic Crypt",
    "chest": "Trillium Chest",
    "score": 598
  },
  {
    "player": "MiniAdo",
    "source": "Level 20 epic Crypt",
    "chest": "Priest's Chest",
    "score": 598
  },
  {
    "player": "MiniAdo",
    "source": "Level 20 epic Crypt",
    "chest": "Priest's Chest",
    "score": 598
  },
  {
    "player": "MiniAdo",
    "source": "Level 20 epic Crypt",
    "chest": "Ancient Warrior's Chest",
    "score": 598
  },
  {
    "player": "MiniAdo",
    "source": "Level 20 epic Crypt",
    "chest": "Ancient Warrior's Chest",
    "score": 598
  },
  {
    "player": "MiniAdo",
    "source": "Level 20 epic Crypt",
    "chest": "Priest's Chest",
    "score": 598
  },
  {
    "player": "MiniAdo",
    "source": "Level 20 epic Crypt",
    "chest": "Trillium Chest",
    "score": 598
  },
  {
    "player": "MiniAdo",
    "source": "Level 20 epic Crypt",
    "chest": "Priest's Chest",
    "score": 598
  },
  {
    "player": "MiniAdo",
    "source": "Level 20 epic Crypt",
    "chest": "Priest's Chest",
    "score": 598
  },
  {
    "player": "MiniAdo",
    "source": "Level 20 epic Crypt",
    "chest": "Trillium Chest",
    "score": 598
  },
  {
    "player": "MiniAdo",
    "source": "Level 20 epic Crypt",
    "chest": "Trillium Chest",
    "score": 598
  },
  {
    "player": "MiniAdo",
    "source": "Level 20 epic Crypt",
    "chest": "Trillium Chest",
    "score": 598
  },
  {
    "player": "MiniAdo",
    "source": "Level 20 epic Crypt",
    "chest": "Trillium Chest",
    "score": 598
  },
  {
    "player": "MiniAdo",
    "source": "Level 20 epic Crypt",
    "chest": "Trillium Chest",
    "score": 598
  },
  {
    "player": "MiniAdo",
    "source": "Level 20 epic Crypt",
    "chest": "Trillium Chest",
    "score": 598
  },
  {
    "player": "MiniAdo",
    "source": "Level 20 rare Crypt",
    "chest": "Rare Dragon Chest",
    "score": 319
  },
  {
    "player": "KHARMA",
    "source": "Level 25 Crypt",
    "chest": "Elegant Chest",
    "score": 550
  },
  {
    "player": "KHARMA",
    "source": "Level 25 Crypt",
    "chest": "Orc Chest",
    "score": 550
  },
  {
    "player": "KHARMA",
    "source": "Level 25 Crypt",
    "chest": "Orc Chest",
    "score": 550
  },
  {
    "player": "KHARMA",
    "source": "Level 25 rare Crypt",
    "chest": "Rare Dragon Chest",
    "score": 800
  },
  {
    "player": "KHARMA",
    "source": "Level 25 rare Crypt",
    "chest": "Rare Dragon Chest",
    "score": 800
  },
  {
    "player": "MiniAdo",
    "source": "Level 20 Crypt",
    "chest": "Orc Chest",
    "score": 167
  },
  {
    "player": "KHARMA",
    "source": "Level 25 epic Crypt",
    "chest": "Harpy Chest",
    "score": 1000
  },
  {
    "player": "MiniAdo",
    "source": "Level 20 Crypt",
    "chest": "Orc Chest",
    "score": 167
  },
  {
    "player": "KHARMA",
    "source": "Level 25 epic Crypt",
    "chest": "Harpy Chest",
    "score": 1000
  },
  {
    "player": "MiniAdo",
    "source": "Level 25 Crypt",
    "chest": "Orc Chest",
    "score": 550
  },
  {
    "player": "MiniAdo",
    "source": "Level 25 Crypt",
    "chest": "Sand Chest",
    "score": 550
  },
  {
    "player": "MiniAdo",
    "source": "Level 25 Crypt",
    "chest": "Sand Chest",
    "score": 550
  },
  {
    "player": "Ditaxe",
    "source": "Level 10 Crypt",
    "chest": "Elegant Chest",
    "score": 35
  },
  {
    "player": "Ditaxe",
    "source": "Level 15 Citadel",
    "chest": "Elven Citadel Chest",
    "score": 30
  },
  {
    "player": "MiniAdo",
    "source": "Level 25 Crypt",
    "chest": "Orc Chest",
    "score": 550
  },
  {
    "player": "MiniAdo",
    "source": "Level 25 Crypt",
    "chest": "Sand Chest",
    "score": 550
  },
  {
    "player": "Ditaxe",
    "source": "Level 20 Crypt",
    "chest": "Mayan Chest",
    "score": 167
  },
  {
    "player": "Ditaxe",
    "source": "Level 20 Citadel",
    "chest": "Cursed Citadel Chest",
    "score": 50
  },
  {
    "player": "MiniAdo",
    "source": "Level 25 Crypt",
    "chest": "Sand Chest",
    "score": 550
  },
  {
    "player": "Ditaxe",
    "source": "Level 10 Crypt",
    "chest": "Bone Chest",
    "score": 35
  },
  {
    "player": "Ditaxe",
    "source": "Level 15 Crypt",
    "chest": "Forgotten Chest",
    "score": 75
  },
  {
    "player": "MiniAdo",
    "source": "Level 25 Crypt",
    "chest": "Cobra Chest",
    "score": 550
  },
  {
    "player": "Ditaxe",
    "source": "Level 15 Crypt",
    "chest": "Cobra Chest",
    "score": 75
  },
  {
    "player": "Ditaxe",
    "source": "Level 15 Crypt",
    "chest": "Bone Chest",
    "score": 75
  },
  {
    "player": "Ditaxe",
    "source": "Level 15 Crypt",
    "chest": "Infernal Chest",
    "score": 75
  },
  {
    "player": "Ditaxe",
    "source": "Level 25 rare Crypt",
    "chest": "Rare Dragon Chest",
    "score": 800
  },
  {
    "player": "Ditaxe",
    "source": "Level 25 Citadel",
    "chest": "Cursed Citadel Chest",
    "score": 120
  },
  {
    "player": "Hair Weave Killa",
    "source": "Level 15 Crypt",
    "chest": "Stone Chest",
    "score": 75
  },
  {
    "player": "Hair Weave Killa",
    "source": "Level 10 rare Crypt",
    "chest": "Rare Dragon Chest",
    "score": 66
  },
  {
    "player": "Hair Weave Killa",
    "source": "Level 20 rare Crypt",
    "chest": "Rare Dragon Chest",
    "score": 319
  },
  {
    "player": "Hair Weave Killa",
    "source": "Level 20 Crypt",
    "chest": "Mayan Chest",
    "score": 167
  },
  {
    "player": "Thutmose III",
    "source": "Level 15 Citadel",
    "chest": "Elven Citadel Chest",
    "score": 30
  },
  {
    "player": "SANGEETA",
    "source": "Clan wealth",
    "chest": "Common Chest of Wealth",
    "score": 0
  },
  {
    "player": "SANGEETA",
    "source": "Clan wealth",
    "chest": "Common Chest of Wealth",
    "score": 0
  },
  {
    "player": "SANGEETA",
    "source": "Clan wealth",
    "chest": "ncommon Chest of Wealth",
    "score": 0
  },
  {
    "player": "SANGEETA",
    "source": "Clan wealth",
    "chest": "Rare Chest of Wealth",
    "score": 0
  },
  {
    "player": "SANGEETA",
    "source": "Clan wealth",
    "chest": "Epic Chest of Wealth",
    "score": 0
  },
  {
    "player": "Auzar",
    "source": "Level 15 Crypt",
    "chest": "Cobra Chest",
    "score": 75
  },
  {
    "player": "Auzar",
    "source": "Level 20 Crypt",
    "chest": "Infernal Chest",
    "score": 167
  },
  {
    "player": "Auzar",
    "source": "Level 15 Crypt",
    "chest": "Infernal Chest",
    "score": 75
  },
  {
    "player": "Auzar",
    "source": "Level 20 rare Crypt",
    "chest": "Rare Dragon Chest",
    "score": 319
  },
  {
    "player": "Auzar",
    "source": "Level 20 epic Crypt",
    "chest": "White Wood Chest",
    "score": 598
  },
  {
    "player": "Auzar",
    "source": "Level 20 Crypt",
    "chest": "Gnome Workshop Chest",
    "score": 167
  },
  {
    "player": "Auzar",
    "source": "Level 15 epic Crypt",
    "chest": "Trillium Chest",
    "score": 308
  },
  {
    "player": "Eufrozyna",
    "source": "Level 25 Crypt",
    "chest": "Mayan Chest",
    "score": 550
  },
  {
    "player": "Eufrozyna",
    "source": "Level 20 Crypt",
    "chest": "Mayan Chest",
    "score": 167
  },
  {
    "player": "Eufrozyna",
    "source": "Level 20 Crypt",
    "chest": "Mayan Chest",
    "score": 167
  },
  {
    "player": "Eufrozyna",
    "source": "Level 20 rare Crypt",
    "chest": "Rare Dragon Chest",
    "score": 319
  },
  {
    "player": "Eufrozyna",
    "source": "Level 20 rare Crypt",
    "chest": "Rare Dragon Chest",
    "score": 319
  },
  {
    "player": "Eufrozyna",
    "source": "Level 20 rare Crypt",
    "chest": "Rare Dragon Chest",
    "score": 319
  },
  {
    "player": "Salka",
    "source": "Level 15 rare Crypt",
    "chest": "Rare Dragon Chest",
    "score": 130
  },
  {
    "player": "Eufrozyna",
    "source": "Level 20 rare Crypt",
    "chest": "Rare Dragon Chest",
    "score": 319
  },
  {
    "player": "Salka",
    "source": "Level 15 rare Crypt",
    "chest": "Rare Dragon Chest",
    "score": 130
  },
  {
    "player": "Salka",
    "source": "Level 15 rare Crypt",
    "chest": "Rare Dragon Chest",
    "score": 130
  },
  {
    "player": "Salka",
    "source": "Level 15 rare Crypt",
    "chest": "Rare Dragon Chest",
    "score": 130
  },
  {
    "player": "Salka",
    "source": "Level 15 rare Crypt",
    "chest": "Rare Dragon Chest",
    "score": 130
  },
  {
    "player": "Salka",
    "source": "Level 15 rare Crypt",
    "chest": "Rare Dragon Chest",
    "score": 130
  },
  {
    "player": "Salka",
    "source": "Level 15 rare Crypt",
    "chest": "Rare Dragon Chest",
    "score": 130
  },
  {
    "player": "Salka",
    "source": "Level 25 rare Crypt",
    "chest": "Rare Dragon Chest",
    "score": 800
  },
  {
    "player": "Salka",
    "source": "Level 25 rare Crypt",
    "chest": "Rare Dragon Chest",
    "score": 800
  },
  {
    "player": "Eufrozyna",
    "source": "Level 20 Citadel",
    "chest": "Cursed Citadel Chest",
    "score": 50
  },
  {
    "player": "Salka",
    "source": "Level 25 Crypt",
    "chest": "Forgotten Chest",
    "score": 550
  },
  {
    "player": "Eufrozyna",
    "source": "Level 20 rare Crypt",
    "chest": "Rare Dragon Chest",
    "score": 319
  },
  {
    "player": "Conjulas",
    "source": "Level 10 Crypt",
    "chest": "Elegant Chest",
    "score": 35
  },
  {
    "player": "Eufrozyna",
    "source": "Level 20 Crypt",
    "chest": "Mayan Chest",
    "score": 167
  },
  {
    "player": "Bomrin",
    "source": "Level 20 rare Crypt",
    "chest": "Rare Dragon Chest",
    "score": 319
  },
  {
    "player": "Conjulas",
    "source": "Level 15 Crypt",
    "chest": "Gnome Workshop Chest",
    "score": 75
  },
  {
    "player": "Conjulas",
    "source": "Level 10 Crypt",
    "chest": "Sand Chest",
    "score": 35
  },
  {
    "player": "Bomrin",
    "source": "Level 20 rare Crypt",
    "chest": "Rare Dragon Chest",
    "score": 319
  },
  {
    "player": "island",
    "source": "Level 25 epic Crypt",
    "chest": "Turtle Chest",
    "score": 1000
  },
  {
    "player": "island",
    "source": "Level 25 epic Crypt",
    "chest": "House of Horrors Chest",
    "score": 1000
  },
  {
    "player": "island",
    "source": "Level 25 Crypt",
    "chest": "Orc Chest",
    "score": 550
  },
  {
    "player": "McGeyerver",
    "source": "Level 10 Crypt",
    "chest": "Orc Chest",
    "score": 35
  },
  {
    "player": "island",
    "source": "Level 25 Crypt",
    "chest": "Barbarian Chest",
    "score": 550
  },
  {
    "player": "Thutmose III",
    "source": "Level 15 Citadel",
    "chest": "Elven Citadel Chest",
    "score": 30
  },
  {
    "player": "island",
    "source": "Level 25 Crypt",
    "chest": "Mayan Chest",
    "score": 550
  },
  {
    "player": "island",
    "source": "Level 25 epic Crypt",
    "chest": "Priest's Chest",
    "score": 1000
  },
  {
    "player": "Thutmose III",
    "source": "Level 15 Citadel",
    "chest": "Elven Citadel Chest",
    "score": 30
  },
  {
    "player": "Thutmose III",
    "source": "Level 15 Citadel",
    "chest": "Elven Citadel Chest",
    "score": 30
  },
  {
    "player": "McGeyerver",
    "source": "Level 10 Crypt",
    "chest": "Gnome Workshop Chest",
    "score": 35
  },
  {
    "player": "Thutmose III",
    "source": "Level 15 Citadel",
    "chest": "Elven Citadel Chest",
    "score": 30
  },
  {
    "player": "Thutmose III",
    "source": "Level 15 Citadel",
    "chest": "Elven Citadel Chest",
    "score": 30
  },
  {
    "player": "SüLocann 171",
    "source": "Bank",
    "chest": "Golden Chest",
    "score": 340
  },
  {
    "player": "SüLocann 171",
    "source": "Bank",
    "chest": "Golden Chest",
    "score": 340
  },
  {
    "player": "SüLocann 171",
    "source": "Bank",
    "chest": "Golden Chest",
    "score": 340
  },
  {
    "player": "SüLocann 171",
    "source": "Bank",
    "chest": "Golden Chest",
    "score": 340
  },
  {
    "player": "SüLocann 171",
    "source": "Bank",
    "chest": "Golden Chest",
    "score": 340
  },
  {
    "player": "SüLocann 171",
    "source": "Bank",
    "chest": "Golden Chest",
    "score": 340
  },
  {
    "player": "Pipper",
    "source": "Bank",
    "chest": "Golden Chest",
    "score": 340
  },
  {
    "player": "Pipper",
    "source": "Bank",
    "chest": "Golden Chest",
    "score": 340
  },
  {
    "player": "Pipper",
    "source": "Bank",
    "chest": "Golden Chest",
    "score": 340
  },
  {
    "player": "Linfiren",
    "source": "Bank",
    "chest": "Precious Chest",
    "score": 670
  },
  {
    "player": "Linfiren",
    "source": "Bank",
    "chest": "Precious Chest",
    "score": 670
  },
  {
    "player": "Linfiren",
    "source": "Bank",
    "chest": "Precious Chest",
    "score": 670
  },
  {
    "player": "KHARMA",
    "source": "Bank",
    "chest": "Golden Chest",
    "score": 340
  },
  {
    "player": "KHARMA",
    "source": "Bank",
    "chest": "Golden Chest",
    "score": 340
  },
  {
    "player": "KHARMA",
    "source": "Bank",
    "chest": "Golden Chest",
    "score": 340
  },
  {
    "player": "SüLocann 171",
    "source": "Bank",
    "chest": "Golden Chest",
    "score": 340
  },
  {
    "player": "SüLocann 171",
    "source": "Bank",
    "chest": "Golden Chest",
    "score": 340
  },
  {
    "player": "SüLocann 171",
    "source": "Bank",
    "chest": "Golden Chest",
    "score": 340
  }
]